[
  {
    "user_id": "user_001",
    "first_seen": "2026-02-13T00:21:14.167746",
    "last_seen": "2026-02-13T00:21:14.167871",
    "status": "active",
    "total_events": 2,
    "total_sessions": 0,
    "properties": {}
  },
  {
    "user_id": "user_002",
    "first_seen": "2026-02-13T00:21:14.167963",
    "last_seen": "2026-02-13T00:21:14.167963",
    "status": "active",
    "total_events": 1,
    "total_sessions": 0,
    "properties": {}
  },
  {
    "user_id": "user_test_1",
    "first_seen": "2026-02-13T00:21:14.173873",
    "last_seen": "2026-02-13T00:21:14.173873",
    "status": "inactive",
    "total_events": 1,
    "total_sessions": 0,
    "properties": {
      "name": "测试用户"
    }
  },
  {
    "user_id": "user_profile_test",
    "first_seen": "2026-02-13T00:21:14.174096",
    "last_seen": "2026-02-13T00:21:14.174293",
    "status": "active",
    "total_events": 3,
    "total_sessions": 1,
    "properties": {}
  },
  {
    "user_id": "user_stats_0",
    "first_seen": "2026-02-13T00:21:14.174513",
    "last_seen": "2026-02-13T00:21:14.174633",
    "status": "active",
    "total_events": 2,
    "total_sessions": 0,
    "properties": {}
  },
  {
    "user_id": "user_stats_1",
    "first_seen": "2026-02-13T00:21:14.174737",
    "last_seen": "2026-02-13T00:21:14.174857",
    "status": "active",
    "total_events": 2,
    "total_sessions": 0,
    "properties": {}
  },
  {
    "user_id": "user_stats_2",
    "first_seen": "2026-02-13T00:21:14.174985",
    "last_seen": "2026-02-13T00:21:14.175140",
    "status": "active",
    "total_events": 2,
    "total_sessions": 0,
    "properties": {}
  },
  {
    "user_id": "user_stats_3",
    "first_seen": "2026-02-13T00:21:14.175260",
    "last_seen": "2026-02-13T00:21:14.175397",
    "status": "active",
    "total_events": 2,
    "total_sessions": 0,
    "properties": {}
  },
  {
    "user_id": "user_stats_4",
    "first_seen": "2026-02-13T00:21:14.175527",
    "last_seen": "2026-02-13T00:21:14.175693",
    "status": "active",
    "total_events": 2,
    "total_sessions": 0,
    "properties": {}
  },
  {
    "user_id": "user_stats_5",
    "first_seen": "2026-02-13T00:21:14.175833",
    "last_seen": "2026-02-13T00:21:14.176002",
    "status": "active",
    "total_events": 2,
    "total_sessions": 0,
    "properties": {}
  },
  {
    "user_id": "user_stats_6",
    "first_seen": "2026-02-13T00:21:14.176157",
    "last_seen": "2026-02-13T00:21:14.176327",
    "status": "active",
    "total_events": 2,
    "total_sessions": 0,
    "properties": {}
  },
  {
    "user_id": "user_stats_7",
    "first_seen": "2026-02-13T00:21:14.176492",
    "last_seen": "2026-02-13T00:21:14.176678",
    "status": "active",
    "total_events": 2,
    "total_sessions": 0,
    "properties": {}
  },
  {
    "user_id": "user_stats_8",
    "first_seen": "2026-02-13T00:21:14.176888",
    "last_seen": "2026-02-13T00:21:14.177093",
    "status": "active",
    "total_events": 2,
    "total_sessions": 0,
    "properties": {}
  },
  {
    "user_id": "user_stats_9",
    "first_seen": "2026-02-13T00:21:14.177285",
    "last_seen": "2026-02-13T00:21:14.177489",
    "status": "active",
    "total_events": 2,
    "total_sessions": 0,
    "properties": {}
  },
  {
    "user_id": "user_retention_final_0",
    "first_seen": "2026-02-13T00:21:14.177716",
    "last_seen": "2026-02-13T00:21:14.180255",
    "status": "active",
    "total_events": 2,
    "total_sessions": 0,
    "properties": {}
  },
  {
    "user_id": "user_retention_final_1",
    "first_seen": "2026-02-13T00:21:14.177932",
    "last_seen": "2026-02-13T00:21:14.180532",
    "status": "active",
    "total_events": 2,
    "total_sessions": 0,
    "properties": {}
  },
  {
    "user_id": "user_retention_final_2",
    "first_seen": "2026-02-13T00:21:14.178153",
    "last_seen": "2026-02-13T00:21:14.180818",
    "status": "active",
    "total_events": 2,
    "total_sessions": 0,
    "properties": {}
  },
  {
    "user_id": "user_retention_final_3",
    "first_seen": "2026-02-13T00:21:14.178378",
    "last_seen": "2026-02-13T00:21:14.181104",
    "status": "active",
    "total_events": 2,
    "total_sessions": 0,
    "properties": {}
  },
  {
    "user_id": "user_retention_final_4",
    "first_seen": "2026-02-13T00:21:14.178617",
    "last_seen": "2026-02-13T00:21:14.181392",
    "status": "active",
    "total_events": 2,
    "total_sessions": 0,
    "properties": {}
  },
  {
    "user_id": "user_retention_final_5",
    "first_seen": "2026-02-13T00:21:14.178871",
    "last_seen": "2026-02-13T00:21:14.181684",
    "status": "active",
    "total_events": 2,
    "total_sessions": 0,
    "properties": {}
  },
  {
    "user_id": "user_retention_final_6",
    "first_seen": "2026-02-13T00:21:14.179154",
    "last_seen": "2026-02-13T00:21:14.181973",
    "status": "active",
    "total_events": 2,
    "total_sessions": 0,
    "properties": {}
  },
  {
    "user_id": "user_retention_final_7",
    "first_seen": "2026-02-13T00:21:14.179421",
    "last_seen": "2026-02-13T00:21:14.179421",
    "status": "active",
    "total_events": 1,
    "total_sessions": 0,
    "properties": {}
  },
  {
    "user_id": "user_retention_final_8",
    "first_seen": "2026-02-13T00:21:14.179701",
    "last_seen": "2026-02-13T00:21:14.179701",
    "status": "active",
    "total_events": 1,
    "total_sessions": 0,
    "properties": {}
  },
  {
    "user_id": "user_retention_final_9",
    "first_seen": "2026-02-13T00:21:14.179976",
    "last_seen": "2026-02-13T00:21:14.179976",
    "status": "active",
    "total_events": 1,
    "total_sessions": 0,
    "properties": {}
  },
  {
    "user_id": "user_filter_test",
    "first_seen": "2026-02-13T00:21:14.182722",
    "last_seen": "2026-02-13T00:21:14.184044",
    "status": "active",
    "total_events": 5,
    "total_sessions": 0,
    "properties": {}
  },
  {
    "user_id": "user_journey",
    "first_seen": "2026-02-13T00:21:14.184418",
    "last_seen": "2026-02-13T00:21:14.185772",
    "status": "active",
    "total_events": 5,
    "total_sessions": 0,
    "properties": {}
  }
]